sdh-org-metrics
setup.cfg
setup.py
SDH_ORG_Metrics.egg-info/PKG-INFO
SDH_ORG_Metrics.egg-info/SOURCES.txt
SDH_ORG_Metrics.egg-info/dependency_links.txt
SDH_ORG_Metrics.egg-info/namespace_packages.txt
SDH_ORG_Metrics.egg-info/requires.txt
SDH_ORG_Metrics.egg-info/top_level.txt
sdh/__init__.py
sdh/metrics/__init__.py
sdh/metrics/org/__init__.py
sdh/metrics/org/api.py
sdh/metrics/org/config.py
sdh/metrics/org/store.py