Metadata-Version: 1.1
Name: SDH-ORG-Metrics
Version: 0.15.0a0
Summary: A service that calculates a small set of quantitative metrics on data from Organization.
Home-page: https://github.com/smartdeveloperhub/sdh-org-metrics
Author: Alejandro F. Carrera
Author-email: alej4fc@gmail.com
License: Apache 2
Download-URL: https://github.com/smartdeveloperhub/sdh-org-metrics
Keywords: linked-data,ontology,path,sdh,metrics
Platform: UNKNOWN
